odkewa/__init__.py
odkewa/expression_converter.py
odkewa/json2html.py
odkewa/odkewa.py
odkewa/odkewa_parser.py
odkewa/populate_xmeta.py
odkewa/xls2json.py
odkewa/static/angular.min.js
odkewa/static/favicon.ico
odkewa/static/iri128.png
odkewa/static/jquery-3.3.1.min.js
odkewa/static/ng-file-upload-shim.min.js
odkewa/static/ng-file-upload.min.js
odkewa/templates/index.html
odkewa-0.1.0.dist-info/AUTHORS
odkewa-0.1.0.dist-info/LICENSE
odkewa-0.1.0.dist-info/METADATA
odkewa-0.1.0.dist-info/WHEEL
odkewa-0.1.0.dist-info/top_level.txt
odkewa-0.1.0.dist-info/RECORD
