Metadata-Version: 2.1
Name: odkewa
Version: 0.1.0
Summary: Data collection platform based on ODK standards
Home-page: https://bitbucket.org/iridl/odkewa
Author: Innokentiy Kumshayev
Author-email: kumshkesh@gmail.com
License: UNKNOWN
Project-URL: Bug Reports, https://bitbucket.org/iridl/odkewa/issues
Platform: UNKNOWN
Classifier: Programming Language :: Python :: 3
Classifier: License :: OSI Approved :: BSD License
Classifier: Operating System :: OS Independent
Requires-Python: >= 3.7
Requires-Dist: psycopg2 (==2.8.*)
Requires-Dist: pycrypto (==2.6.*)
Requires-Dist: flask (==1.0.*)
Requires-Dist: pyjade (==4.0.*)
Requires-Dist: queuepool (==1.3.*)
Requires-Dist: pyaconf (==0.7.*)
Requires-Dist: pyyaml (==5.1.*)
